Metadata-Version: 2.1
Name: MadEngine-server-mess
Version: 1.1.0
Summary: mess_server
Author: MadEngine
Author-email: scorpio-84@mail.ru
Requires-Dist: PyQt6
Requires-Dist: sqlalchemy
